README.rst
setup.py
tox_setuptools.py
tox_setuptools.egg-info/PKG-INFO
tox_setuptools.egg-info/SOURCES.txt
tox_setuptools.egg-info/dependency_links.txt
tox_setuptools.egg-info/entry_points.txt
tox_setuptools.egg-info/top_level.txt