Metadata-Version: 1.0
Name: tox-setuptools
Version: 1.3.3
Summary: Tox integration with setuptools
Home-page: https://github.com/2m/tox-setuptools
Author: UNKNOWN
Author-email: UNKNOWN
License: Apache 2
Platform: UNKNOWN
